knapsack/__init__.py
knapsack/py.typed
knapsack-0.3.1.dist-info/METADATA
knapsack-0.3.1.dist-info/WHEEL
knapsack-0.3.1.dist-info/licenses/LICENSE
knapsack-0.3.1.dist-info/RECORD
