Metadata-Version: 2.3
Name: knapsack
Version: 0.3.1
Summary: `knapsack` is a package for for solving knapsack problem.
Project-URL: homepage, https://github.com/SaitoTsutomu/knapsack
Author-email: Saito Tsutomu <tsutomu7@hotmail.co.jp>
License: Apache-2.0
License-File: LICENSE
Classifier: Development Status :: 1 - Planning
Classifier: License :: OSI Approved :: Apache Software License
Classifier: Programming Language :: Python
Classifier: Topic :: Scientific/Engineering
Classifier: Topic :: Software Development
Requires-Python: >=3.11
